[{"act": "Sailors and Soldiers (Gifts for Land Settlement) Act 1916 (repealed)", "year": 1916, "section": "1", "section_title": " Power to accept and administer gifts for settlement of ex-sailors and soldiers on land.", "section_text": "1 . . . . . . . . . . . . . . . . . . . . . . . . . . . . . . . ."}, {"act": "Sailors and Soldiers (Gifts for Land Settlement) Act 1916 (repealed)", "year": 1916, "section": "2", "section_title": " Short title and saving.", "section_text": "2 . . . . . . . . . . . . . . . . . . . . . . . . . . . . . . . ."}]