[{"act": "Age of Legal Capacity (Scotland) Act 1991", "year": 1991, "section": "1", "section_title": " Age of legal capacity.", "section_text": "1 1 As from the commencement of this Act\u2014 a a person under the age of 16 years shall, subject to section 2 below, have no legal capacity to enter into any transaction; b a person of or over the age of 16 years shall have legal capacity to enter into any transaction. 2 Subject to section 8 below, any reference in any enactment to a pupil (other than in the context of education or training) or to a person under legal disability or incapacity by reason of nonage shall, insofar as it relates to any time after the commencement of this Act, be construed as a reference to a person under the age of 16 years. 3 Nothing in this Act shall\u2014 a apply to any transaction entered into before the commencement of this Act; b confer any legal capacity on any person who is under legal disability or incapacity other than by reason of nonage; c affect the delictual or criminal responsibility of any person; d affect any enactment which lays down an age limit expressed in years for any particular purpose; e prevent any person under the age of 16 years from receiving or holding any right, title or interest; f affect any existing rule of law or practice whereby\u2014 i any civil proceedings may be brought or defended, or any step in civil proceedings may be taken, in the name of a person under the age of 16 years  in relation to whom there is no person entitled to act as his legal representative (within the meaning of Part I of the Children (Scotland) Act 1995), or where there is such a person  is unable (whether by reason of conflict of interest or otherwise) or refuses to bring or defend such proceedings or take such step; ii the court may, in any civil proceedings, appoint a curator ad litem to a person under the age of 16 years; iii the court may, in relation to the approval of an arrangement under section 1 of the  Trusts (Scotland) Act 1961, appoint a curator ad litem to a person of or over the age of 16 years but under the age of 18 years; iv the court may appoint a curator bonis to any person; g prevent any person under the age of 16 years from  exercising parental responsibilities and parental rights (within the meaning of sections 1(3) and 2(4) respectively of the Children (Scotland) Act 1995) in relation to any child of his. 4 Any existing rule of law relating to the legal capacity of minors and pupils which is inconsistent with the provisions of this Act shall cease to have effect. 5 Any existing rule of law relating to reduction of a transaction on the ground of minority and lesion shall cease to have effect."}, {"act": "Age of Legal Capacity (Scotland) Act 1991", "year": 1991, "section": "2", "section_title": " Exceptions to general rule.", "section_text": "2 1 A person under the age of 16 years shall have legal capacity to enter into a transaction\u2014 a of a kind commonly entered into by persons of his age and circumstances, and b on terms which are not unreasonable. 2 A person of or over the age of 12 years shall have testamentary capacity, including legal capacity to exercise by testamentary writing any power of appointment. 3 A person of or over the age of 12 years shall have legal capacity to consent to the making of an adoption order in relation to him ... 4 A person under the age of 16 years shall have legal capacity to consent on his own behalf to any surgical, medical or dental procedure or treatment where, in the opinion of a qualified medical practitioner attending him, he is capable of understanding the nature and possible consequences of the procedure or treatment. 4ZA For the purposes of subsection (4), the storage of gametes in accordance with the Human Fertilisation and Embryology Act 1990 is to be treated as a medical procedure. 4ZB A person under the age of 16 years shall have legal capacity to consent to the use of the person's human cells in accordance with Schedule 3 to the Human Fertilisation and Embryology Act 1990 for the purposes of a project of research where the person is capable of understanding the nature of the research; and in this subsection  \u201c human cells \u201d has the same meaning as in that Schedule.    4A A person under the age of sixteen years shall have legal capacity to instruct a solicitor, in connection with any civil matter, where that person has a general understanding of what it means to do so; and without prejudice to the generality of this subsection a person twelve years of age or more shall be presumed to be of sufficient age and maturity to have such understanding. 4B A person who by virtue of subsection (4A) above has legal capacity to instruct a solicitor shall also have legal capacity to sue, or to defend, in any civil proceedings. 4C Subsections (4A) and (4B) above are without prejudice to any question of legal capacity arising in connection with any criminal matter. 5 Any transaction\u2014 a which a person under the age of 16 years purports to enter into after the commencement of this Act, and b in relation to which that person does not have legal capacity by virtue of this section, shall be void."}, {"act": "Age of Legal Capacity (Scotland) Act 1991", "year": 1991, "section": "3", "section_title": " Setting aside of transactions.", "section_text": "3 1 A person under the age of 21 years (\u201cthe applicant\u201d) may make application to the court to set aside a transaction which he entered into while he was of or over the age of 16 years but under the age of 18 years and which is a prejudicial transaction. 2 In this section \u201c prejudicial transaction \u201d means a transaction which\u2014 a an adult, exercising reasonable prudence, would not have entered into in the circumstances of the applicant at the time of entering into the transaction, and b has caused or is likely to cause substantial prejudice to the applicant. 3 Subsection (1) above shall not apply to\u2014 a the exercise of testamentary capacity; b the exercise by testamentary writing of any power of appointment; c the giving of consent to the making of an adoption order; d the bringing or defending of, or the taking of any step in, civil proceedings; e the giving of consent to any surgical, medical or dental procedure or treatment; f a transaction in the course of the applicant\u2019s trade, business or profession; g a transaction into which any other party was induced to enter by virtue of any fraudulent misrepresentation by the applicant as to age or other material fact; h a transaction ratified by the applicant after he attained the age of 18 years and in the knowledge that it could be the subject of an application to the court under this section to set it aside; or j a transaction ratified by the court under section 4 below. 4 Where an application to set aside a transaction can be made or could have been made under this section by the person referred to in subsection (1) above, such application may instead be made by that person\u2019s executor, trustee in bankruptcy, trustee acting under a trust deed for creditors or curator bonis at any time prior to the date on which that person attains or would have attained the age of 21 years. 5 An application under this section to set aside a transaction may be made\u2014 a by an action in the Court of Session or the sheriff court, or b by an incidental application in other proceedings in such court, and the court may make an order setting aside the transaction and such further order, if any, as seems appropriate to the court in order to give effect to the rights of the parties."}, {"act": "Age of Legal Capacity (Scotland) Act 1991", "year": 1991, "section": "4", "section_title": " Ratification by court of proposed transaction.", "section_text": "4 1 Where a person of or over the age of 16 years but under the age of 18 years proposes to enter into a transaction which, if completed, could be the subject of an application to the court under section 3 above to set aside, all parties to the proposed transaction may make a joint application to have it ratified by the court. 2 The court shall not grant an application under this section if it appears to the court that an adult, exercising reasonable prudence and in the circumstances of the person referred to in subsection (1) above, would not enter into the transaction. 3 An application under this section shall be made by means of a summary application\u2014 a to the sheriff of the sheriffdom in which any of the parties to the proposed transaction resides, or b where none of the said parties resides in Scotland, to the sheriff at Edinburgh, and the decision of the sheriff on such application shall be final."}, {"act": "Age of Legal Capacity (Scotland) Act 1991", "year": 1991, "section": "5", "section_title": " Guardians of persons under 16.", "section_text": "5 1 Except insofar as otherwise provided in Schedule 1 to this Act, as from the commencement of this Act any reference in any rule of law, enactment or document to the tutor  . . . of a pupil child shall be construed as a reference to  a person entitled to act as a child\u2019s legal representative (within the meaning of Part I of the Children (Scotland) Act 1995), and any reference to the tutory of such a child shall be construed as a reference to the entitlement to act as a child\u2019s legal representative enjoyed by a person by, under or by virtue of the said Part I. 2 Subject to section 1(3)(f) above, as from the commencement of this Act no guardian of a person under the age of 16 years shall be appointed as such except under  section 7 of the Children (Scotland) Act 1995. 3 As from the commencement of this Act, no person shall, by reason of age alone, be subject to the curatory of another person. 4 As from the commencement of this Act, no person shall be appointed as factor loco tutoris."}, {"act": "Age of Legal Capacity (Scotland) Act 1991", "year": 1991, "section": "6", "section_title": " Attainment of age.", "section_text": "6 1 The time at which a person attains a particular age expressed in years shall be taken to be the beginning of the relevant anniversary of the date of his birth. 2 Where a person has been born on 29th February in a leap year, the relevant anniversary in any year other than a leap year shall be taken to be 1st March. 3 The provisions of this section shall apply only to a relevant anniversary which occurs after the commencement of this Act."}, {"act": "Age of Legal Capacity (Scotland) Act 1991", "year": 1991, "section": "7", "section_title": " Acquisition of domicile.", "section_text": "7 . . . . . . . . . . . . . . . . . . . . . . . . . . . . . . . ."}, {"act": "Age of Legal Capacity (Scotland) Act 1991", "year": 1991, "section": "8", "section_title": " Transitional provision.", "section_text": "8 Where any person referred to in section 6(4)(b), 17(3), 18(3) or 18A(2) of the  Prescription and Limitation (Scotland) Act 1973 as having been under legal disability by reason of nonage was of or over the age of 16 years but under the age of 18 years immediately before the commencement of this Act, any period prior to such commencement shall not be reckoned as, or as part of, the period of 5 years, or (as the case may be) 3 years, specified respectively in section 6, 17, 18 or 18A of that Act."}, {"act": "Age of Legal Capacity (Scotland) Act 1991", "year": 1991, "section": "9", "section_title": " Interpretation.", "section_text": "9 In this Act, unless the context otherwise requires\u2014 \u201c existing \u201d means existing immediately before the commencement of this Act; . . . \u201c transaction \u201d means a transaction having legal effect, and includes\u2014 any unilateral transaction; the exercise of testamentary capacity; the exercise of any power of appointment; the giving by a person of any consent having legal effect; the bringing or defending of, or the taking of any step in, civil proceedings; acting as arbiter or trustee; acting as an instrumentary witness."}, {"act": "Age of Legal Capacity (Scotland) Act 1991", "year": 1991, "section": "10", "section_title": " Amendments and repeals.", "section_text": "10 1 The enactments mentioned in Schedule 1 to this Act shall have effect subject to the amendments therein specified. 2 The enactments specified in Schedule 2 to this Act are repealed to the extent specified in the third column of that Schedule."}, {"act": "Age of Legal Capacity (Scotland) Act 1991", "year": 1991, "section": "11", "section_title": " Short title, commencement and extent.", "section_text": "11 1 This Act may be cited as the Age of Legal Capacity (Scotland) Act 1991. 2 This Act shall come into force at the end of the period of two months beginning with the date on which it is passed. 3 This Act shall extend to Scotland only."}]