[{"act": "Industrial and Provident Societies Act 1967 (repealed)", "year": 1967, "section": "1", "section_title": " Charges on assets of English and Welsh societies.", "section_text": "1 . . . . . . . . . . . . . . . . . . . . . . . . . . . . . . . ."}, {"act": "Industrial and Provident Societies Act 1967 (repealed)", "year": 1967, "section": "2", "section_title": " Application of Part I.", "section_text": "2 . . . . . . . . . . . . . . . . . . . . . . . . . . . . . . . ."}, {"act": "Industrial and Provident Societies Act 1967 (repealed)", "year": 1967, "section": "3", "section_title": " Application to registered societies of provisions relating to floating charges.", "section_text": "3 . . . . . . . . . . . . . . . . . . . . . . . . . . . . . . . ."}, {"act": "Industrial and Provident Societies Act 1967 (repealed)", "year": 1967, "section": "4", "section_title": " Filing of information relating to charges.", "section_text": "4 . . . . . . . . . . . . . . . . . . . . . . . . . . . . . . . ."}, {"act": "Industrial and Provident Societies Act 1967 (repealed)", "year": 1967, "section": "5", "section_title": " Supplemental provisions.", "section_text": "5 . . . . . . . . . . . . . . . . . . . . . . . . . . . . . . . ."}, {"act": "Industrial and Provident Societies Act 1967 (repealed)", "year": 1967, "section": "6", "section_title": " Interpretation and application of Part II.", "section_text": "6 . . . . . . . . . . . . . . . . . . . . . . . . . . . . . . . ."}, {"act": "Industrial and Provident Societies Act 1967 (repealed)", "year": 1967, "section": "7", "section_title": " Interpretation,  et ceteralaetc. \u2014general.", "section_text": "7 . . . . . . . . . . . . . . . . . . . . . . . . . . . . . . . ."}, {"act": "Industrial and Provident Societies Act 1967 (repealed)", "year": 1967, "section": "8", "section_title": " Citation, commencement and extent.", "section_text": "8 . . . . . . . . . . . . . . . . . . . . . . . . . . . . . . . ."}]