[{"act": "Public Accounts and Charges Act 1891 (repealed)", "year": 1891, "section": "1", "section_title": " Abolition of office of Receiver-General of Inland Revenue and provision as to Inland Revenue moneys.", "section_text": "1 . . . . . . . . . . . . . . . . . . . . . . . . . . . . . . . ."}, {"act": "Public Accounts and Charges Act 1891 (repealed)", "year": 1891, "section": "2", "section_title": ". . . . . . . . . . . . . . . . . . . . . . . . . . . . . . . .", "section_text": "2"}, {"act": "Public Accounts and Charges Act 1891 (repealed)", "year": 1891, "section": "3", "section_title": ". . . . . . . . . . . . . . . . . . . . . . . . . . . . . . . . ", "section_text": "3"}, {"act": "Public Accounts and Charges Act 1891 (repealed)", "year": 1891, "section": "4", "section_title": ". . . . . . . . . . . . . . . . . . . . . . . . . . . . . . . . ", "section_text": "4"}, {"act": "Public Accounts and Charges Act 1891 (repealed)", "year": 1891, "section": "5", "section_title": ". . . . . . . . . . . . . . . . . . . . . . . . . . . . . . . . ", "section_text": "5"}, {"act": "Public Accounts and Charges Act 1891 (repealed)", "year": 1891, "section": "6", "section_title": " Short title.", "section_text": "6 . . . . . . . . . . . . . . . . . . . . . . . . . . . . . . . ."}]