[{"act": "Criminal Procedure (Scotland) Act 1887 (repealed 1.4.1996)", "year": 1887, "section": "12.", "section_title": "  . . . . . . . . . . . . . . . . . . . . . . . . . . . . . . . .", "section_text": "1"}, {"act": "Criminal Procedure (Scotland) Act 1887 (repealed 1.4.1996)", "year": 1887, "section": "3", "section_title": ". . . . . . . . . . . . . . . . . . . . . . . . . . . . . . . .", "section_text": "3"}, {"act": "Criminal Procedure (Scotland) Act 1887 (repealed 1.4.1996)", "year": 1887, "section": "444.", "section_title": "  . . . . . . . . . . . . . . . . . . . . . . . . . . . . . . . .", "section_text": "4"}, {"act": "Criminal Procedure (Scotland) Act 1887 (repealed 1.4.1996)", "year": 1887, "section": "45", "section_title": "  . . . . . . . . . . . . . . . . . . . . . . . . . . . . . . . .", "section_text": "45"}, {"act": "Criminal Procedure (Scotland) Act 1887 (repealed 1.4.1996)", "year": 1887, "section": "46", "section_title": " Sittings of High Court.", "section_text": "46 . . . . . . . . . . . . . . . . . . . . . . . . . . . . . . . . "}, {"act": "Criminal Procedure (Scotland) Act 1887 (repealed 1.4.1996)", "year": 1887, "section": "4776.", "section_title": "  . . . . . . . . . . . . . . . . . . . . . . . . . . . . . . . .", "section_text": "47"}, {"act": "Criminal Procedure (Scotland) Act 1887 (repealed 1.4.1996)", "year": 1887, "section": "77", "section_title": "  . . . . . . . . . . . . . . . . . . . . . . . . . . . . . . . .", "section_text": "77"}, {"act": "Criminal Procedure (Scotland) Act 1887 (repealed 1.4.1996)", "year": 1887, "section": "78", "section_title": " Short title.", "section_text": "78 This Act may be cited as the Criminal Procedure (Scotland) Act 1887."}]