[{"act": "Northern Ireland Arms Decommissioning (Amendment) Act 2002", "year": 2002, "section": "1", "section_title": " Extension of amnesty period", "section_text": "1 1 Section 2 of the Northern Ireland Arms Decommissioning Act 1997 (c. 7) (duration of decommissioning scheme) is amended as follows. 2 In subsection (2)(a), for \u201cthe first anniversary of the day on which this Act is passed\u201d substitute  \u201c                27th February 2003              \u201d . 3 In subsection (3)(b), for \u201cmore than five years after the day on which this Act is passed\u201d substitute  \u201c                later than 27th February 2007              \u201d . 4 If this section comes into force after 26th February 2002, a scheme which would at any time have been a decommissioning scheme for the purposes of the Northern Ireland Arms Decommissioning Act 1997 had this section come into force on that date, is to be treated as having been such a scheme at that time."}, {"act": "Northern Ireland Arms Decommissioning (Amendment) Act 2002", "year": 2002, "section": "2", "section_title": " Short title", "section_text": "2 This Act may be cited as the Northern Ireland Arms Decommissioning (Amendment) Act 2002."}]