[{"act": "Habeas Corpus Act 1862", "year": 1862, "section": "1", "section_title": " Writ not to issue out of England into any Colony, having a Court with Authority to grant such Writ.", "section_text": "1 No writ of habeas corpus shall issue out of England, by authority of any judge or court of justice therein, into any colony or foreign dominion of the Crown where Her Majesty has a lawfully established court or courts of justice having authority to grant and issue the said writ, and to ensure the due execution thereof throughout such colony or dominion."}, {"act": "Habeas Corpus Act 1862", "year": 1862, "section": "2", "section_title": " Not to affect Right of Appeal to Her Majesty in Council.", "section_text": "2 Provided, that nothing in this Act contained shall affect or interfere with any right of appeal to Her Majesty in Council now by law existing."}]