[{"act": "Fixed-term Parliaments Act 2011 (repealed)", "year": 2011, "section": "1", "section_title": "Polling days for parliamentary general elections", "section_text": "1 . . . . . . . . . . . . . . . . . . . . . . . . . . . . . . . ."}, {"act": "Fixed-term Parliaments Act 2011 (repealed)", "year": 2011, "section": "2", "section_title": "Early parliamentary general elections", "section_text": "2 . . . . . . . . . . . . . . . . . . . . . . . . . . . . . . . ."}, {"act": "Fixed-term Parliaments Act 2011 (repealed)", "year": 2011, "section": "3", "section_title": "Dissolution of Parliament", "section_text": "3 . . . . . . . . . . . . . . . . . . . . . . . . . . . . . . . ."}, {"act": "Fixed-term Parliaments Act 2011 (repealed)", "year": 2011, "section": "4", "section_title": "General election for Scottish Parliament not to fall on same date as parliamentary general election under section 1(2)", "section_text": "4 . . . . . . . . . . . . . . . . . . . . . . . . . . . . . . . ."}, {"act": "Fixed-term Parliaments Act 2011 (repealed)", "year": 2011, "section": "5", "section_title": "General election for National Assembly for Wales not to fall on same date as parliamentary general election under section 1(2)", "section_text": "5 . . . . . . . . . . . . . . . . . . . . . . . . . . . . . . . ."}, {"act": "Fixed-term Parliaments Act 2011 (repealed)", "year": 2011, "section": "6", "section_title": "Supplementary provisions", "section_text": "6 . . . . . . . . . . . . . . . . . . . . . . . . . . . . . . . ."}, {"act": "Fixed-term Parliaments Act 2011 (repealed)", "year": 2011, "section": "7", "section_title": "Final provisions", "section_text": "7 . . . . . . . . . . . . . . . . . . . . . . . . . . . . . . . ."}]