[{"act": "Universities (Scotland) Act 1922", "year": 1922, "section": "1", "section_title": ". . . . . . . . . . . . . . . . . . . . . . . . . . . . . . . . ", "section_text": "1"}, {"act": "Universities (Scotland) Act 1922", "year": 1922, "section": "2", "section_title": " Lecturers and readers to be members of general councils. ", "section_text": "2 A lecturer or reader appointed by the university court of a Scottish university who has held the office of lecturer or reader therein for one year shall thenceforward, during his tenure of that office, be a member of the general council of that university and entitled to all the rights and privileges of a member of council although his name is not entered in the register of the council: . . . "}, {"act": "Universities (Scotland) Act 1922", "year": 1922, "section": "3", "section_title": " Citation and construction.", "section_text": "3 This Act may be cited as the Universities (Scotland) Act 1922, and shall, so far as is consistent with the tenor thereof, be read and construed along with the  Universities (Scotland) Act 1858, and the  Universities (Scotland) Act 1889, and those Acts and this Act may be cited together as the Universities (Scotland) Acts, 1858 to 1922."}]